sinkr/__init__.py
sinkr/sink.py
sinkr/source.py
sinkr-0.2.5.dist-info/METADATA
sinkr-0.2.5.dist-info/WHEEL
sinkr-0.2.5.dist-info/RECORD
